pyswyft/__init__.py
pyswyft/exceptions.py
pyswyft/pyswyft.py
pyswyft/endpoints/__init__.py
pyswyft/endpoints/accounts.py
pyswyft/endpoints/addresses.py
pyswyft/endpoints/apirequest.py
pyswyft/endpoints/decorators.py
pyswyft/endpoints/history.py
pyswyft/endpoints/markets.py
pyswyft/endpoints/orders.py
pyswyft-0.2.0.dist-info/LICENSE.md
pyswyft-0.2.0.dist-info/METADATA
pyswyft-0.2.0.dist-info/WHEEL
pyswyft-0.2.0.dist-info/entry_points.txt
pyswyft-0.2.0.dist-info/top_level.txt
pyswyft-0.2.0.dist-info/RECORD
