Metadata-Version: 2.1
Name: pyswyft
Version: 0.2.0
Summary: Python wrapper for Swyftx API
Home-page: http://pyswyft.lachlanteale.com/
Author: Lachlan Teale
Author-email: lachlan.teale@gmail.com
License: MIT
Keywords: Swyftx Crypto API wrapper REST
Platform: UNKNOWN
Classifier: License :: OSI Approved :: MIT License
Classifier: Intended Audience :: Developers
Classifier: Intended Audience :: Financial and Insurance Industry
Classifier: Operating System :: OS Independent
Classifier: Development Status :: 3 - Alpha
Classifier: Natural Language :: English
Classifier: Topic :: Software Development :: Libraries :: Python Modules
Classifier: Programming Language :: Python
Classifier: Programming Language :: Python :: 3.6
Classifier: Programming Language :: Python :: 3.7
Classifier: Programming Language :: Python :: 3.8
Classifier: Programming Language :: Python :: 3.9
License-File: LICENSE.md
